apx/__init__.py
apx/apx_logging.py
apx/apxdeploy_config.py
apx/authentication.py
apx/check.py
apx/cli.py
apx/cloud_stores.py
apx/core.py
apx/dag.py
apx/exceptions.py
apx/execution.py
apx/global_user_state.py
apx/optimizer.py
apx/resources.py
apx/status_lib.py
apx/task.py
apx/adaptors/__init__.py
apx/adaptors/aws.py
apx/adaptors/azure.py
apx/adaptors/cloudflare.py
apx/adaptors/common.py
apx/adaptors/cudo.py
apx/adaptors/docker.py
apx/adaptors/gcp.py
apx/adaptors/ibm.py
apx/adaptors/kubernetes.py
apx/adaptors/oci.py
apx/adaptors/runpod.py
apx/adaptors/vsphere.py
apx/apxlet/__init__.py
apx/apxlet/apxlet.py
apx/apxlet/attempt_skylet.py
apx/apxlet/autostop_lib.py
apx/apxlet/configs.py
apx/apxlet/constants.py
apx/apxlet/events.py
apx/apxlet/job_lib.py
apx/apxlet/log_lib.py
apx/apxlet/log_lib.pyi
apx/apxlet/subprocess_daemon.py
apx/apxlet/providers/__init__.py
apx/apxlet/providers/command_runner.py
apx/apxlet/providers/ibm/__init__.py
apx/apxlet/providers/ibm/node_provider.py
apx/apxlet/providers/ibm/utils.py
apx/apxlet/providers/ibm/vpc_provider.py
apx/apxlet/providers/lambda_cloud/__init__.py
apx/apxlet/providers/lambda_cloud/node_provider.py
apx/apxlet/providers/oci/__init__.py
apx/apxlet/providers/oci/node_provider.py
apx/apxlet/providers/oci/query_helper.py
apx/apxlet/providers/oci/utils.py
apx/apxlet/providers/scp/__init__.py
apx/apxlet/providers/scp/config.py
apx/apxlet/providers/scp/node_provider.py
apx/apxlet/ray_patches/__init__.py
apx/backends/__init__.py
apx/backends/backend.py
apx/backends/backend_utils.py
apx/backends/cloud_vm_ray_backend.py
apx/backends/docker_utils.py
apx/backends/local_docker_backend.py
apx/backends/wheel_utils.py
apx/backends/monkey_patches/monkey_patch_ray_up.py
apx/backends/playground/demo_dockerutils.py
apx/benchmark/__init__.py
apx/benchmark/benchmark_state.py
apx/benchmark/benchmark_utils.py
apx/callbacks/setup.py
apx/callbacks/sky_callback/__init__.py
apx/callbacks/sky_callback/api.py
apx/callbacks/sky_callback/base.py
APX_V1_APX-0.1.0.dist-info/LICENSE
APX_V1_APX-0.1.0.dist-info/METADATA
APX_V1_APX-0.1.0.dist-info/WHEEL
APX_V1_APX-0.1.0.dist-info/top_level.txt
APX_V1_APX-0.1.0.dist-info/RECORD
